mopidy/__init__.py
mopidy/__main__.py
mopidy/backend.py
mopidy/commands.py
mopidy/exceptions.py
mopidy/ext.py
mopidy/httpclient.py
mopidy/listener.py
mopidy/mixer.py
mopidy/py.typed
mopidy/zeroconf.py
mopidy/audio/__init__.py
mopidy/audio/actor.py
mopidy/audio/constants.py
mopidy/audio/listener.py
mopidy/audio/scan.py
mopidy/audio/tags.py
mopidy/audio/utils.py
mopidy/config/__init__.py
mopidy/config/default.conf
mopidy/config/keyring.py
mopidy/config/schemas.py
mopidy/config/types.py
mopidy/config/validators.py
mopidy/core/__init__.py
mopidy/core/actor.py
mopidy/core/history.py
mopidy/core/library.py
mopidy/core/listener.py
mopidy/core/mixer.py
mopidy/core/playback.py
mopidy/core/playlists.py
mopidy/core/tracklist.py
mopidy/file/__init__.py
mopidy/file/backend.py
mopidy/file/ext.conf
mopidy/file/library.py
mopidy/http/__init__.py
mopidy/http/actor.py
mopidy/http/ext.conf
mopidy/http/handlers.py
mopidy/http/data/clients.html
mopidy/http/data/favicon.ico
mopidy/http/data/mopidy.css
mopidy/internal/__init__.py
mopidy/internal/deprecation.py
mopidy/internal/deps.py
mopidy/internal/formatting.py
mopidy/internal/gi.py
mopidy/internal/http.py
mopidy/internal/jsonrpc.py
mopidy/internal/log.py
mopidy/internal/models.py
mopidy/internal/network.py
mopidy/internal/path.py
mopidy/internal/playlists.py
mopidy/internal/process.py
mopidy/internal/storage.py
mopidy/internal/timer.py
mopidy/internal/validation.py
mopidy/internal/versioning.py
mopidy/internal/xdg.py
mopidy/m3u/__init__.py
mopidy/m3u/backend.py
mopidy/m3u/ext.conf
mopidy/m3u/playlists.py
mopidy/m3u/translator.py
mopidy/models/__init__.py
mopidy/models/fields.py
mopidy/models/immutable.py
mopidy/models/serialize.py
mopidy/softwaremixer/__init__.py
mopidy/softwaremixer/ext.conf
mopidy/softwaremixer/mixer.py
mopidy/stream/__init__.py
mopidy/stream/actor.py
mopidy/stream/ext.conf
Mopidy-3.4.2.dist-info/LICENSE
Mopidy-3.4.2.dist-info/METADATA
Mopidy-3.4.2.dist-info/WHEEL
Mopidy-3.4.2.dist-info/entry_points.txt
Mopidy-3.4.2.dist-info/top_level.txt
Mopidy-3.4.2.dist-info/RECORD
