Metadata-Version: 2.1
Name: Mopidy
Version: 3.4.2
Summary: Mopidy is an extensible music server written in Python
Home-page: https://mopidy.com/
Author: Stein Magnus Jodal
Author-email: stein.magnus@jodal.no
License: Apache License, Version 2.0
Project-URL: Documentation, https://docs.mopidy.com/
Project-URL: Discourse forum, https://discourse.mopidy.com/
Project-URL: Zulip chat, https://mopidy.zulipchat.com/
Project-URL: Source, https://github.com/mopidy/mopidy
Project-URL: Issues, https://github.com/mopidy/mopidy/issues
Classifier: Development Status :: 5 - Production/Stable
Classifier: Environment :: No Input/Output (Daemon)
Classifier: Intended Audience :: End Users/Desktop
Classifier: License :: OSI Approved :: Apache Software License
Classifier: Operating System :: MacOS :: MacOS X
Classifier: Operating System :: POSIX :: Linux
Classifier: Programming Language :: Python :: 3
Classifier: Programming Language :: Python :: 3.7
Classifier: Programming Language :: Python :: 3.8
Classifier: Programming Language :: Python :: 3.9
Classifier: Programming Language :: Python :: 3.10
Classifier: Programming Language :: Python :: 3.11
Classifier: Programming Language :: Python :: 3.12
Classifier: Topic :: Multimedia :: Sound/Audio :: Players
Requires-Python: >=3.7
License-File: LICENSE
Requires-Dist: Pykka>=2.0.1
Requires-Dist: requests>=2.0
Requires-Dist: setuptools
Requires-Dist: tornado>=4.4
Provides-Extra: docs
Requires-Dist: pygraphviz; extra == "docs"
Requires-Dist: sphinx; extra == "docs"
Requires-Dist: sphinx_rtd_theme; extra == "docs"
Provides-Extra: lint
Requires-Dist: black; extra == "lint"
Requires-Dist: check-manifest; extra == "lint"
Requires-Dist: flake8; extra == "lint"
Requires-Dist: flake8-black; extra == "lint"
Requires-Dist: flake8-bugbear; extra == "lint"
Requires-Dist: flake8-isort; extra == "lint"
Requires-Dist: isort; extra == "lint"
Requires-Dist: mypy; extra == "lint"
Requires-Dist: pep8-naming; extra == "lint"
Requires-Dist: types-requests; extra == "lint"
Requires-Dist: types-setuptools; extra == "lint"
Provides-Extra: test
Requires-Dist: pytest; extra == "test"
Requires-Dist: pytest-cov; extra == "test"
Requires-Dist: responses; extra == "test"
Provides-Extra: dev
Requires-Dist: pygraphviz; extra == "dev"
Requires-Dist: sphinx; extra == "dev"
Requires-Dist: sphinx_rtd_theme; extra == "dev"
Requires-Dist: black; extra == "dev"
Requires-Dist: check-manifest; extra == "dev"
Requires-Dist: flake8; extra == "dev"
Requires-Dist: flake8-black; extra == "dev"
Requires-Dist: flake8-bugbear; extra == "dev"
Requires-Dist: flake8-isort; extra == "dev"
Requires-Dist: isort; extra == "dev"
Requires-Dist: mypy; extra == "dev"
Requires-Dist: pep8-naming; extra == "dev"
Requires-Dist: types-requests; extra == "dev"
Requires-Dist: types-setuptools; extra == "dev"
Requires-Dist: pytest; extra == "dev"
Requires-Dist: pytest-cov; extra == "dev"
Requires-Dist: responses; extra == "dev"
Requires-Dist: tox; extra == "dev"
